dollars/__init__.py
dollars-0.2.0.dist-info/DESCRIPTION.rst
dollars-0.2.0.dist-info/METADATA
dollars-0.2.0.dist-info/RECORD
dollars-0.2.0.dist-info/WHEEL
dollars-0.2.0.dist-info/metadata.json
dollars-0.2.0.dist-info/top_level.txt
