Metadata-Version: 2.0
Name: dollars
Version: 0.2.0
Summary: Converts everything to dollars using up to date rates for free
Home-page: http://github.com/aerupt/dollars
Author: Lasse Schuirmann
Author-email: lasse.schuirmann@gmail.com
License: MIT
Platform: UNKNOWN
Requires-Dist: requests (~=2.13.0)
